flask_guard/__init__.py
flask_guard/config.py
flask_guard/middleware.py
flask_guard/rules.py
flask_guard/utils.py
safe_flask-2.1.0.dist-info/licenses/LICENSE
safe_flask-2.1.0.dist-info/METADATA
safe_flask-2.1.0.dist-info/WHEEL
safe_flask-2.1.0.dist-info/top_level.txt
safe_flask-2.1.0.dist-info/RECORD
