Metadata-Version: 2.4
Name: safe-flask
Version: 2.1.0
Summary: A plug-and-play firewall library for Flask applications.
Author-email: CodeGuardianSOF <securex39@gmail.com>
License: MIT License
Project-URL: Homepage, https://github.com/CodeGuardianSOF/FlaskGuard
Classifier: Programming Language :: Python :: 3
Classifier: Framework :: Flask
Classifier: License :: OSI Approved :: MIT License
Classifier: Operating System :: OS Independent
Requires-Python: >=3.6
License-File: LICENSE
Requires-Dist: Flask>=1.1.2
Dynamic: license-file
